deepdefend/__init__.py
deepdefend/attacks.py
deepdefend/defenses.py
deepdefend-0.1.4.dist-info/licenses/LICENSE
deepdefend-0.1.4.dist-info/METADATA
deepdefend-0.1.4.dist-info/WHEEL
deepdefend-0.1.4.dist-info/top_level.txt
deepdefend-0.1.4.dist-info/RECORD
